{
  "createdBy": {
    "user": {
      "email": "Matthew@levinelegalservices.com",
      "id": "c7f37529-e089-4b7b-a230-890249a8d69b",
      "displayName": "Matthew Levine"
    }
  },
  "createdDateTime": "2025-10-01T15:22:01Z",
  "eTag": "\"{504E9D0C-646F-42F6-B9B0-697032805F5D},3\"",
  "id": "01YY66BGQMTVHFA33E6ZBLTMDJOAZIAX25",
  "lastModifiedBy": {
    "user": {
      "email": "Matthew@levinelegalservices.com",
      "id": "c7f37529-e089-4b7b-a230-890249a8d69b",
      "displayName": "Matthew Levine"
    }
  },
  "lastModifiedDateTime": "2025-06-02T14:50:47Z",
  "name": "SOPs",
  "parentReference": {
    "driveType": "documentLibrary",
    "driveId": "b!h1ZUioTppUufgSXSnMchs-6DFblC5YNCsdfy7k-ghhOWiwXFZMfpQ76cRS11GoNU",
    "id": "01YY66BGVLY7SE3HUVMZCLNUGPTBOKCJQT",
    "name": "24-682-00003 SnowCap CAMLO Operations",
    "path": "/drives/b!h1ZUioTppUufgSXSnMchs-6DFblC5YNCsdfy7k-ghhOWiwXFZMfpQ76cRS11GoNU/root:/LL Matters (Essential)/24-682-00003 -- Stream/24-682-00003 SnowCap CAMLO Operations",
    "siteId": "8a545687-e984-4ba5-9f81-25d29cc721b3"
  },
  "webUrl": "https://levinellp.sharepoint.com/sites/LegalMatters/Shared%20Documents/LL%20Matters%20(Essential)/24-682-00003%20--%20Stream/24-682-00003%20SnowCap%20CAMLO%20Operations/SOPs",
  "cTag": "\"c:{504E9D0C-646F-42F6-B9B0-697032805F5D},0\"",
  "fileSystemInfo": {
    "createdDateTime": "2025-10-01T15:22:01Z",
    "lastModifiedDateTime": "2025-06-02T14:50:47Z"
  },
  "folder": {
    "childCount": 0
  },
  "shared": {
    "scope": "users"
  },
  "size": 0
}